pyantiword/__init__.py
pyantiword/antiword
pyantiword/antiword_wrapper.py
pyantiword/antiword_share/8859-1.txt
pyantiword/antiword_share/8859-10.txt
pyantiword/antiword_share/8859-11.txt
pyantiword/antiword_share/8859-13.txt
pyantiword/antiword_share/8859-14.txt
pyantiword/antiword_share/8859-15.txt
pyantiword/antiword_share/8859-16.txt
pyantiword/antiword_share/8859-2.txt
pyantiword/antiword_share/8859-3.txt
pyantiword/antiword_share/8859-4.txt
pyantiword/antiword_share/8859-5.txt
pyantiword/antiword_share/8859-6.txt
pyantiword/antiword_share/8859-7.txt
pyantiword/antiword_share/8859-8.txt
pyantiword/antiword_share/8859-9.txt
pyantiword/antiword_share/MacCyrillic.txt
pyantiword/antiword_share/MacRoman.txt
pyantiword/antiword_share/UTF-8.txt
pyantiword/antiword_share/cp1250.txt
pyantiword/antiword_share/cp1251.txt
pyantiword/antiword_share/cp1252.txt
pyantiword/antiword_share/cp437.txt
pyantiword/antiword_share/cp850.txt
pyantiword/antiword_share/cp852.txt
pyantiword/antiword_share/cp862.txt
pyantiword/antiword_share/cp864.txt
pyantiword/antiword_share/cp866.txt
pyantiword/antiword_share/fontnames
pyantiword/antiword_share/koi8-r.txt
pyantiword/antiword_share/koi8-u.txt
pyantiword/antiword_share/roman.txt
pyantiword-0.1.2.dist-info/licenses/LICENSE.md
pyantiword-0.1.2.dist-info/METADATA
pyantiword-0.1.2.dist-info/WHEEL
pyantiword-0.1.2.dist-info/top_level.txt
pyantiword-0.1.2.dist-info/RECORD
