Metadata-Version: 2.4
Name: pyantiword
Version: 0.1.2
Summary: Python wrapper for antiword with bundled binary and data files
Author: Vitor Hugo Moreira Reis
License-File: LICENSE.md
Dynamic: author
Dynamic: description
Dynamic: description-content-type
Dynamic: license-file
Dynamic: summary
